fileserve/__init__.py
fileserve/fileserve.py
fileserve-0.1.0.dist-info/METADATA
fileserve-0.1.0.dist-info/WHEEL
fileserve-0.1.0.dist-info/RECORD
