Metadata-Version: 2.3
Name: fileserve
Version: 0.1.0
Summary: Add your description here
Author-email: avycado13 <108358183+avycado13@users.noreply.github.com>
Requires-Python: >=3.8
Requires-Dist: click>=8.1.7
